setup.py
mle_distributions/Binomialdistribution.py
mle_distributions/Gaussiandistribution.py
mle_distributions/Generaldistribution.py
mle_distributions/__init__.py
mle_distributions.egg-info/PKG-INFO
mle_distributions.egg-info/SOURCES.txt
mle_distributions.egg-info/dependency_links.txt
mle_distributions.egg-info/not-zip-safe
mle_distributions.egg-info/top_level.txt