Metadata-Version: 1.0
Name: mle-distributions
Version: 1.0
Summary: Gaussian and Binomial distributions
Home-page: UNKNOWN
Author: Mona Hajimomeni
Author-email: mona1983@gmail.com
License: UNKNOWN
Platform: UNKNOWN
